devtools_morse/__init__.py
devtools_morse-1.0.1.dist-info/METADATA
devtools_morse-1.0.1.dist-info/WHEEL
devtools_morse-1.0.1.dist-info/top_level.txt
devtools_morse-1.0.1.dist-info/RECORD
