Metadata-Version: 2.1
Name: devtools_morse
Version: 1.0.1
Summary: Morse code translator
Home-page: https://devtools.at/tools/morse-code
Author: DevTools.at
Author-email: hello@devtools.at
Project-URL: Homepage, https://devtools.at/tools/morse-code
Project-URL: Repository, https://github.com/devtools-at/morse-code
Classifier: Development Status :: 4 - Beta
Classifier: Intended Audience :: Developers
Classifier: License :: OSI Approved :: MIT License
Classifier: Programming Language :: Python :: 3
Requires-Python: >=3.8
